design.sv
module counter4(
    input clk,
    output reg [3:0] count
);

always @(posedge clk)
begin
    count <= count + 1;
end

endmodule

testbench.sv
module tb();

reg clk;
wire [3:0] count;
counter4 inst(clk, count);

initial begin
    $dumpfile("test.vcd");
    $dumpvars(0, tb);
end

// Clock Generation
initial begin
    clk = 0;
    forever #5ns clk = ~clk;
end

// Simulation
initial begin
    #100ns;
    $finish;
end
endmodule

test.vcd
$version Generated by VerilatedVcd $end
$timescale 1ns $end
 $scope module tb $end
  $var wire 1 # clk $end
  $var wire 4 $ count [3:0] $end
  $scope module inst $end
   $var wire 1 # clk $end
   $var wire 4 $ count [3:0] $end
  $upscope $end
 $upscope $end
$enddefinitions $end


#0
0#
b0000 $
#5
1#
b0001 $
#10
0#
#15
1#
b0010 $
#20
0#
#25
1#
b0011 $
#30
0#
#35
1#
b0100 $
#40
0#
#45
1#
b0101 $
#50
0#
#55
1#
b0110 $
#60
0#
#65
1#
b0111 $
#70
0#
#75
1#
b1000 $
#80
0#
#85
1#
b1001 $
#90
0#
#95
1#
b1010 $
