design.sv
module register4(
    input clk,
    input rst,
    input [3:0] D,
    output reg [3:0] Q
);

always @(posedge clk)
begin
    if (rst)
        Q <= 4'b0000;
    else
        Q <= D;
end

endmodule

testbench.sv
module tb();
reg clk, rst;
reg [3:0] D;
wire [3:0] Q;
  register4 uut (  .clk(clk),  .rst(rst), .D(D), .Q(Q) );
initial begin
    $dumpfile("test.vcd");
    $dumpvars(0, tb);
end
initial begin
    clk = 0;
    forever #5 clk = ~clk;
end
initial begin
    rst = 1;
    D = 4'b0000;
    #10;
    rst = 0;
    D = 4'b0001;
    #10;
    D = 4'b1010;
    #10;
    D = 4'b1111;
    #10;
    D = 4'b0101;
    #10;
    rst = 1;
    #10;
    rst = 0;
    D = 4'b1100;
    #10;
    $finish;
end endmodule

test.vcd
$version Generated by VerilatedVcd $end
$timescale 1ns $end
 $scope module tb $end
  $var wire 1 # clk $end
  $var wire 1 $ rst $end
  $var wire 4 % D [3:0] $end
  $var wire 4 & Q [3:0] $end
  $scope module uut $end
   $var wire 1 # clk $end
   $var wire 1 $ rst $end
   $var wire 4 % D [3:0] $end
   $var wire 4 & Q [3:0] $end
  $upscope $end
 $upscope $end
$enddefinitions $end


#0
0#
1$
b0000 %
b0000 &
#5
1#
#10
0#
0$
b0001 %
#15
1#
b0001 &
#20
0#
b1010 %
#25
1#
b1010 &
#30
0#
b1111 %
#35
1#
b1111 &
#40
0#
b0101 %
#45
1#
b0101 &
#50
0#
1$
#55
1#
b0000 &
#60
0#
0$
b1100 %
#65
1#
b1100 &
